allure_pytest_ext/__init__.py
allure_pytest_ext/plugin.py
allure_pytest_ext-2.15.0.dist-info/METADATA
allure_pytest_ext-2.15.0.dist-info/WHEEL
allure_pytest_ext-2.15.0.dist-info/entry_points.txt
allure_pytest_ext-2.15.0.dist-info/licenses/LICENSE
allure_pytest_ext-2.15.0.dist-info/RECORD
