Metadata-Version: 2.4
Name: allure-pytest-ext
Version: 2.15.0
Summary: Extensions for allure-pytest: propagate step failures and aggregate step failures
Project-URL: Homepage, https://github.com/
Project-URL: Repository, https://github.com/
Author-email: Rami Hasan <hsn.rami@gmail.com>
License: MIT
License-File: LICENSE
Keywords: aggregate,allure,propagate,pytest,report,testing
Classifier: Framework :: Pytest
Classifier: License :: OSI Approved :: MIT License
Classifier: Programming Language :: Python :: 3
Classifier: Programming Language :: Python :: 3 :: Only
Classifier: Programming Language :: Python :: 3.8
Classifier: Programming Language :: Python :: 3.9
Classifier: Programming Language :: Python :: 3.10
Classifier: Programming Language :: Python :: 3.11
Classifier: Programming Language :: Python :: 3.12
Requires-Python: >=3.8.1
Requires-Dist: allure-pytest<=2.15.0,>=2.13.3
